pushshift_py/__init__.py
pushshift_py/pushshift_api.py
pushshift_py/pushshift_api_minimal.py
pushshift_py/rate_limit_cache.py
pushshift.py-0.1.2.dist-info/LICENSE
pushshift.py-0.1.2.dist-info/METADATA
pushshift.py-0.1.2.dist-info/WHEEL
pushshift.py-0.1.2.dist-info/top_level.txt
pushshift.py-0.1.2.dist-info/RECORD
