Metadata-Version: 1.2
Name: pushshift.py
Version: 0.1.2
Summary: Pushshift.io API Wrapper for reddit.com search endpoints
Home-page: https://github.com/typenil/pushshift.py
Author: David Marx (original), typenil (fork)
Author-email: code@typenil.com
License: Simplified BSD License
Keywords: reddit api wrapper pushshift
Platform: UNKNOWN
Classifier: Development Status :: 3 - Alpha
Classifier: Environment :: Console
Classifier: Intended Audience :: Developers
Classifier: License :: OSI Approved :: BSD License
Classifier: Natural Language :: English
Classifier: Operating System :: OS Independent
Classifier: Programming Language :: Python
Classifier: Programming Language :: Python :: 3
Classifier: Programming Language :: Python :: 3.4
Classifier: Programming Language :: Python :: 3.5
Classifier: Programming Language :: Python :: 3.6
Classifier: Programming Language :: Python :: 3 :: Only
Classifier: Programming Language :: Python :: Implementation :: CPython
Classifier: Topic :: Utilities
Requires-Python: >=3
